[{"city": "F\u00fczesabony", "phone": "36 542 061"}, {"city": "Budapest", "phone": "30 333 6011"}, {"city": "Balaton\u0151sz\u00f6d", "phone": "30 936 6301"}, {"city": "Budapest", "phone": "30 784 6768"}, {"city": "Sz\u00e9kesfeh\u00e9rv\u00e1r", "phone": "30 073 0546"}, {"city": "V\u00e1rpalota", "phone": "30 228 3269"}, {"city": "Feh\u00e9rgyarmat", "phone": "30 515 9847"}, {"city": "Balatonf\u00fcred", "phone": "87 512 537"}, {"city": "Balatonf\u00fcred", "phone": "87 512 556"}, {"city": "Balatonf\u00fcred", "phone": "87 512 570"}, {"city": "Balatonf\u00fcred", "phone": "87 512 512"}, {"city": "Balatonf\u00fcred", "phone": "87 512 594"}, {"city": "Balatonf\u00fcred", "phone": "87 512 523"}, {"city": "Nagykanizsa", "phone": "30 265 9047"}, {"city": "Budapest", "phone": "30 162 6691"}, {"city": "Budapest", "phone": "30 543 1319"}, {"city": "\u00dcll\u00e9s", "phone": "30 481 0452"}, {"city": "Nagykanizsa", "phone": "30 288 2572"}, {"city": "Nagykanizsa", "phone": "30 267 3906"}, {"city": "Szombathely", "phone": "30 169 2367"}]